_faest_cffi.abi3.so
faest/__init__.py
faest/core.py
include/__init__.py
include/aes.h
include/aesni.h
include/bavc.h
include/compat.h
include/config.h
include/cpu.h
include/endian_compat.h
include/faest.h
include/faest_128f.h
include/faest_128s.h
include/faest_192f.h
include/faest_192s.h
include/faest_256f.h
include/faest_256s.h
include/faest_aes.h
include/faest_defines.h
include/faest_em_128f.h
include/faest_em_128s.h
include/faest_em_192f.h
include/faest_em_192s.h
include/faest_em_256f.h
include/faest_em_256s.h
include/faest_impl.h
include/fields.h
include/hash_shake.h
include/instances.h
include/macros.h
include/owf.h
include/parameters.h
include/random_oracle.h
include/randomness.h
include/universal_hashing.h
include/utils.h
include/vole.h
lib/__init__.py
lib/linux/__init__.py
lib/linux/x86_64/__init__.py
lib/macos/__init__.py
lib/macos/arm64/__init__.py
lib/macos/arm64/libfaest.1.dylib
lib/macos/arm64/libfaest.dylib
pyfaest-1.0.15.dist-info/licenses/LICENSE
pyfaest-1.0.15.dist-info/METADATA
pyfaest-1.0.15.dist-info/WHEEL
pyfaest-1.0.15.dist-info/top_level.txt
pyfaest-1.0.15.dist-info/RECORD
