Metadata-Version: 2.1
Name: pyfaest
Version: 1.0.15
Summary: Python bindings for FAEST post-quantum signature scheme
Home-page: https://github.com/Shreyas582/pyfaest
Author: PyFAEST Contributors
Author-email: 
Maintainer: Shreyas Sankpal
Maintainer-email: shreyas.sankpal@nyu.edu
License: MIT
Project-URL: Homepage, https://github.com/Shreyas582/pyfaest
Project-URL: Documentation, https://github.com/Shreyas582/pyfaest/blob/main/README.md
Project-URL: Repository, https://github.com/Shreyas582/pyfaest
Project-URL: Bug Tracker, https://github.com/Shreyas582/pyfaest/issues
Project-URL: Changelog, https://github.com/Shreyas582/pyfaest/blob/main/CHANGELOG.md
Keywords: cryptography,post-quantum,signatures,faest,pqc,quantum-resistant
Classifier: Development Status :: 4 - Beta
Classifier: Intended Audience :: Developers
Classifier: Intended Audience :: Science/Research
Classifier: Topic :: Security :: Cryptography
Classifier: Programming Language :: Python :: 3
Classifier: Programming Language :: Python :: 3.7
Classifier: Programming Language :: Python :: 3.8
Classifier: Programming Language :: Python :: 3.9
Classifier: Programming Language :: Python :: 3.10
Classifier: Programming Language :: Python :: 3.11
Classifier: Programming Language :: Python :: 3.12
Classifier: Programming Language :: Python :: Implementation :: CPython
Classifier: Programming Language :: C
Classifier: Operating System :: POSIX :: Linux
Requires-Python: >=3.7
License-File: LICENSE
Requires-Dist: cffi>=1.15.0
Requires-Dist: setuptools>=60.0.0
Provides-Extra: dev
Requires-Dist: pytest>=7.0; extra == "dev"
Requires-Dist: pytest-cov>=4.0; extra == "dev"
